sidetable/__init__.py
sidetable/sidetable.py
sidetable-0.9.1.dist-info/AUTHORS.md
sidetable-0.9.1.dist-info/LICENSE
sidetable-0.9.1.dist-info/METADATA
sidetable-0.9.1.dist-info/WHEEL
sidetable-0.9.1.dist-info/top_level.txt
sidetable-0.9.1.dist-info/RECORD
