Metadata-Version: 2.1
Name: sidetable
Version: 0.9.1
Summary: sidetable builds simple but useful summary tables of your data
Home-page: https://github.com/chris1610/sidetable
Author: Chris Moffitt
Author-email: chris@moffitts.net
License: MIT license
Keywords: sidetable
Classifier: Development Status :: 4 - Beta
Classifier: Intended Audience :: Developers
Classifier: License :: OSI Approved :: MIT License
Classifier: Natural Language :: English
Classifier: Programming Language :: Python :: 3.6
Requires-Python: >=3.6
License-File: LICENSE
License-File: AUTHORS.md
